{
    "id": "callService",
    "title": { 
        "en": "Call service",
        "de": "Dienst aufrufen",
        "nl": "Roep service aan"
    },
    "titleFormatted": { 
        "en": "Call service [[service]] of domain [[domain]] with data [[data]]",
        "de": "Dienst [[service]] der Domäne [[domain]] mit den Daten [[data]] aufrufen",
        "nl": "Bel service [[service]] van domein [[domain]] met data [[data]]"
    },
    "hint": {
        "en": "Example for light.turn_on: service=turn_on, domain=light, data={'brightness':100, 'entity_id':'light.entityname'}",
        "de": "Beispiel für light.turn_on: service=turn_on, domain=light, data={'brightness':100, 'entity_id':'light.entityname'}",
        "nl": "Voorbeeld voor light.turn_on: service=turn_on, domain=light, data={'brightness':100, 'entity_id':'light.entityname'}"
    },
    "args": [
        {
            "name": "domain",
            "type": "text"
        },
        {
            "name": "service",
            "type": "text"
        },
        {
            "name": "data",
            "type": "text"
        }
    ]
}
